django_vr_payment/__init__.py
django_vr_payment/admin.py
django_vr_payment/apps.py
django_vr_payment/fields.py
django_vr_payment/managers.py
django_vr_payment/settings.py
django_vr_payment/tests.py
django_vr_payment/urls.py
django_vr_payment/views.py
django_vr_payment/migrations/0001_initial.py
django_vr_payment/migrations/0002_auto_20200824_1937.py
django_vr_payment/migrations/__init__.py
django_vr_payment/models/__init__.py
django_vr_payment/models/core.py
django_vr_payment/models/mixins.py
django_vr_payment/models/payment.py
django_vr_payment/models/webhooks.py
django_vr_payment/utils/__init__.py
django_vr_payment/utils/transaction_status.py
django_vr_payment/utils/webhooks.py
django_vr_payment/wrapper/__init__.py
django_vr_payment/wrapper/checkout.py
django_vr_payment/wrapper/transaction.py
django_vr_pay-0.2.0.dist-info/LICENSE
django_vr_pay-0.2.0.dist-info/METADATA
django_vr_pay-0.2.0.dist-info/WHEEL
django_vr_pay-0.2.0.dist-info/top_level.txt
django_vr_pay-0.2.0.dist-info/RECORD
