Metadata-Version: 2.1
Name: django-vr-pay
Version: 0.2.0
Summary: A Django app to handle payment request through vr payment.
Home-page: https://github.com/ParticulateSolutions/django-vr-payment
Author: Particulate Solutions GmbH
Author-email: tech@particulate.me
License: MIT
Platform: UNKNOWN
Classifier: Environment :: Web Environment
Classifier: Framework :: Django
Classifier: Intended Audience :: Developers
Classifier: License :: OSI Approved :: MIT License
Classifier: Operating System :: OS Independent
Classifier: Programming Language :: Python
Classifier: Programming Language :: Python :: 3
Classifier: Programming Language :: Python :: 3 :: Only
Classifier: Programming Language :: Python :: 3.6
Classifier: Programming Language :: Python :: 3.7
Classifier: Programming Language :: Python :: 3.8
Classifier: Topic :: Internet :: WWW/HTTP
Classifier: Topic :: Internet :: WWW/HTTP :: Dynamic Content
Requires-Dist: requests
Requires-Dist: django
Requires-Dist: cryptography
